mmio_rs-0.1.0.dist-info/METADATA
mmio_rs-0.1.0.dist-info/WHEEL
mmio_rs-0.1.0.dist-info/license_files/LICENSE
m2io_tmp/__init__.py
m2io_tmp/m2io_tmp.cpython-38-x86_64-linux-gnu.so
mmio_rs-0.1.0.dist-info/RECORD
